[
    {
        "id": 19,
        "title": "Ролл с жареным Лососем",
        "desc": "Жареный лосось, огурец, сыр сливочный, кунжут,  рис, нори.",
        "price": 400,
        "weight": "240 гр.  8 шт.",
        "img": "../img/products/roll/roll-freelosos.png"
    },
    {
        "id": 20,
        "title": "Ролл с жареным Тунцом",
        "desc": "Жареный тунец, огурец, сыр сливочный, кунжут, рис, нори.",
        "price": 290,
        "weight": "240 гр.  8 шт.",
        "img": "../img/products/roll/roll-freetynec.png"
    },
    {
        "id": 21,
        "title": "Острый ролл с Тунцом",
        "desc": "Тунец, огурец, кунжут, острый соус, рис, нори.",
        "price": 260,
        "weight": "210 гр.  8 шт.",
        "img": "../img/products/roll/roll-hottynec.png"
    },
    {
        "id": 22,
        "title": "Острый ролл с Лососем",
        "desc": "Лосось, огурец, кунжут, острый соус рис, нори.",
        "price": 330,
        "weight": "210 гр.  8 шт.",
        "img": "../img/products/roll/roll-hotlosos.png"
    },
    {
        "id": 23,
        "title": "Ролл Сырный",
        "desc": "Сыр сливочный, пармезан, сыр тостерный, унаги, рис, нори.",
        "price": 260,
        "weight": "240 гр.  8 шт.",
        "img": "../img/products/roll/roll-cheese.png"
    },
    {
        "id": 24,
        "title": "Ролл Цезарь",
        "desc": "Куриное филе, сыр сливочный, помидор, сыр пармезан, чесночный соус, рис, нори.",
        "price": 280,
        "weight": "260 гр.  8 шт.",
        "img": "../img/products/roll/roll-cesar.png"
    },
    {
        "id": 25,
        "title": "Ролл Хиросима",
        "desc": "Лосось фламбе, сыр сливочный, креветка, рис, нори.",
        "price": 590,
        "weight": "280 гр.  8 шт.",
        "img": "../img/products/roll/roll-hirosima.png"
    },
    {
        "id": 26,
        "title": "Ролл Ямомото",
        "desc": "Угорь, сыр сливочный, краб, унаги, кунжут , рис, нори.",
        "price": 560,
        "weight": "280 гр.  8 шт.",
        "img": "../img/products/roll/roll-yamoto.png"
    },
    {
        "id": 27,
        "title": "Ролл Осака",
        "desc": "Угорь, сыр сливочный, лосось, кунжут, унаги, рис, нори.",
        "price": 750,
        "weight": "300 гр.  8 шт.",
        "img": "../img/products/roll/roll-osaka.png"
    },
    {
        "id": 28,
        "title": "Киото",
        "desc": "Угорь, лосось, сыр сливочный, огурец, икра масаго, рис, нори.",
        "price": 550,
        "weight": "270 гр.  8 шт.",
        "img": "../img/products/new/kioto.png"
    },
    {
        "id": 29,
        "title": "Марокко",
        "desc": "Краб, сыр сливочный, огурец, кунжут, икра масаго, рис, нори.",
        "price": 280,
        "weight": "270 гр.  8 шт.",
        "img": "../img/products/new/marokko.png"
    },
    {
        "id": 30,
        "title": "Канада в кунжуте",
        "desc": "Угорь, сыр сливочный, огурец, кунжут, унаги, рис нори.",
        "price": 400,
        "weight": "260 гр.  8 шт.",
        "img": "../img/products/new/kanada.png"
    },
    {
        "id": 31,
        "title": "Радуга",
        "desc": "Лосось, угорь, тунец, сыр сливочный, огурец, авокадо, креветка,унаги, кунжут, рис, нори.",
        "price": 560,
        "weight": "280 гр.  8 шт.",
        "img": "../img/products/new/raduga.png"
    },
    {
        "id": 32,
        "title": "Катана",
        "desc": "Угорь, лосось, сыр сливочный, икра масаго, рис, нори.",
        "price": 800,
        "weight": "290 гр.  8 шт.",
        "img": "../img/products/new/katana.png"
    },
    {
        "id": 33,
        "title": "Такао",
        "desc": "Тунец, сыр сливочный, креветка, огурец, рис, нори.",
        "price": 360,
        "weight": "280 гр.  8 шт.",
        "img": "../img/products/new/takao.png"
    },
    {
        "id": 34,
        "title": "Токио",
        "desc": "Угорь, сыр сливочный, огурец, креветка, унаги, кунжут, рис, нори.",
        "price": 630,
        "weight": "290 гр.  8 шт.",
        "img": "../img/products/new/tokio.png"
    },
    {
        "id": 35,
        "title": "Ролл в стружке тунца",
        "desc": "Угорь, стружка тунца, огурец, сыр сливочный, унаги, рис, нори.",
        "price": 420,
        "weight": "260 гр.  8 шт.",
        "img": "../img/products/new/rollinstr.png"
    }
]